datafc/__init__.py
datafc/sofascore/__init__.py
datafc/sofascore/fetch_coordinates_data.py
datafc/sofascore/fetch_goal_networks_data.py
datafc/sofascore/fetch_lineups_data.py
datafc/sofascore/fetch_match_data.py
datafc/sofascore/fetch_match_odds_data.py
datafc/sofascore/fetch_match_stats_data.py
datafc/sofascore/fetch_momentum_data.py
datafc/sofascore/fetch_past_matches_data.py
datafc/sofascore/fetch_player_stats_data.py
datafc/sofascore/fetch_shots_data.py
datafc/sofascore/fetch_squad_data.py
datafc/sofascore/fetch_standings_data.py
datafc/sofascore/fetch_substitutions_data.py
datafc/sofascore/fetch_team_stats_data.py
datafc/utils/__init__.py
datafc/utils/_config.py
datafc/utils/_save_files.py
datafc/utils/_setup_webdriver.py
datafc-1.5.0.dist-info/LICENSE
datafc-1.5.0.dist-info/METADATA
datafc-1.5.0.dist-info/WHEEL
datafc-1.5.0.dist-info/top_level.txt
datafc-1.5.0.dist-info/RECORD
