Metadata-Version: 2.1
Name: datafc
Version: 1.5.0
Summary: A scalable Python library for fetching, processing, and exporting structured football match data.
Home-page: https://github.com/urazakgul/datafc
Author: Uraz Akgül
Author-email: urazdev@gmail.com
License: MIT
Keywords: football soccer data analytics sofascore selenium
Classifier: Programming Language :: Python :: 3
Classifier: License :: OSI Approved :: MIT License
Classifier: Operating System :: OS Independent
Requires-Python: >=3.8
License-File: LICENSE
Requires-Dist: pandas
Requires-Dist: selenium
Requires-Dist: webdriver-manager
Requires-Dist: openpyxl
